tinytag/__init__.py
tinytag/__main__.py
tinytag/py.typed
tinytag/tinytag.py
tinytag-2.1.1.dist-info/licenses/LICENSE
tinytag-2.1.1.dist-info/WHEEL
tinytag-2.1.1.dist-info/METADATA
tinytag-2.1.1.dist-info/RECORD
