Metadata-Version: 2.4
Name: tinytag
Version: 2.1.1
Summary: Read audio file metadata
Keywords: metadata,audio,music,mp3,m4a,wav,ogg,opus,flac,wma,aiff
Author: Tom Wallroth, Mat (mathiascode)
Requires-Python: >=3.7
Classifier: Programming Language :: Python
Classifier: Programming Language :: Python :: 3
Classifier: Programming Language :: Python :: 3.7
Classifier: Programming Language :: Python :: 3.8
Classifier: Programming Language :: Python :: 3.9
Classifier: Programming Language :: Python :: 3.10
Classifier: Programming Language :: Python :: 3.11
Classifier: Programming Language :: Python :: 3.12
Classifier: Programming Language :: Python :: 3.13
Classifier: License :: OSI Approved :: MIT License
Classifier: Development Status :: 5 - Production/Stable
Classifier: Environment :: Web Environment
Classifier: Intended Audience :: Developers
Classifier: Operating System :: OS Independent
Classifier: Topic :: Internet :: WWW/HTTP
Classifier: Topic :: Multimedia
Classifier: Topic :: Multimedia :: Sound/Audio
Classifier: Topic :: Multimedia :: Sound/Audio :: Analysis
Classifier: Typing :: Typed
License-File: LICENSE
Requires-Dist: coverage ; extra == "tests"
Requires-Dist: mypy ; extra == "tests"
Requires-Dist: pycodestyle ; extra == "tests"
Requires-Dist: pylint ; extra == "tests"
Project-URL: Homepage, https://github.com/tinytag/tinytag
Provides-Extra: tests
